{
  "basicPackages": [
    {
      "name": "基础指导版",
      "targetAudience": "科研入门者或首次投稿者",
      "customerPain": "不知道如何选题、如何开始科研写作、论文逻辑混乱",
      "serviceHighlight": "从选题到结构指导，涵盖基础科研思维建立 + 实用模板 + 精准反馈",
      "price": "¥5800 起",
      "features": [
        "期刊推荐",
        "初稿诊断",
        "通讯作者筛查",
        "Cover Letter指导",
        "投稿系统指导"
      ],
      "serviceContent": "1. 科研选题指导\n2. 论文结构规划\n3. 写作模板提供\n4. 定期反馈与修改建议\n5. 投稿策略指导",
      "serviceDetail": "## 服务概述\n\n基础指导版为科研入门者提供从选题到投稿的全流程指导。包括初步沟通、选题指导、结构规划、写作指导和投稿支持。服务保障包括一对一指导、快速响应和专业团队支持。"
    },
    {
      "name": "标准陪跑版",
      "targetAudience": "有项目基础，但缺乏系统指导的学生或在职科研人员",
      "customerPain": "研究推进效率低、缺乏外部反馈、对命中率焦虑",
      "serviceHighlight": "提供1对1长期陪跑，每阶段定期回顾调整，强化逻辑与创新点提炼",
      "price": "¥6800 起",
      "features": [
        "期刊推荐",
        "初稿诊断",
        "通讯作者筛查",
        "Cover Letter指导",
        "投稿系统指导",
        "答疑支持",
        "状态跟踪"
      ],
      "serviceContent": "1. 科研选题指导\n2. 论文结构规划\n3. 写作模板提供\n4. 定期反馈与修改建议\n5. 投稿策略指导\n6. 全程答疑支持\n7. 投稿状态跟踪",
      "serviceDetail": "## 服务概述\n\n标准陪跑版为有项目基础的研究者提供一对一长期陪跑服务。内容包括选题与规划、写作指导、投稿支持和全程陪跑。特色是一对一专属指导、定期进度回顾、全程答疑支持和投稿状态跟踪。"
    },
    {
      "name": "高阶返修版",
      "targetAudience": "已完成论文初稿或被退稿用户",
      "customerPain": "返修无从下手、审稿意见难以应对、投稿命中率低",
      "serviceHighlight": "专业审稿人思维解析返修路径，模拟投稿修回流程，提升命中率与学术影响力",
      "price": "¥8800 起",
      "features": [
        "期刊推荐",
        "初稿诊断",
        "通讯作者筛查",
        "Cover Letter指导",
        "投稿系统指导",
        "答疑支持",
        "状态跟踪",
        "返修解读",
        "回复信指导"
      ],
      "serviceContent": "1. 科研选题指导\n2. 论文结构规划\n3. 写作模板提供\n4. 定期反馈与修改建议\n5. 投稿策略指导\n6. 全程答疑支持\n7. 投稿状态跟踪\n8. 返修意见解读\n9. 回复信撰写指导",
      "serviceDetail": "## 服务概述\n\n高阶返修版专为已完成论文初稿或被退稿用户设计，提供审稿意见分析、返修方案设计、回复信撰写和全程指导。特色是审稿人视角分析、专业返修指导、回复信撰写支持和全程质量把控。"
    },
    {
      "name": "VIP项目合作",
      "targetAudience": "希望打造高质量SCI/SSCI/A&HCI稿件、申请海外项目用户",
      "customerPain": "时间紧任务重、缺乏专业支持、需要高端资源对接",
      "serviceHighlight": "深度定制化科研解决方案+高阶导师团队+长期陪跑+成果输出保障",
      "price": "¥18000 起",
      "features": [
        "期刊推荐",
        "初稿诊断",
        "通讯作者筛查",
        "Cover Letter指导",
        "投稿系统指导",
        "答疑支持",
        "状态跟踪",
        "返修解读",
        "回复信指导",
        "录用对赌"
      ],
      "serviceContent": "1. 科研选题指导\n2. 论文结构规划\n3. 写作模板提供\n4. 定期反馈与修改建议\n5. 投稿策略指导\n6. 全程答疑支持\n7. 投稿状态跟踪\n8. 返修意见解读\n9. 回复信撰写指导\n10. 项目整体统筹",
      "serviceDetail": "## 服务概述\n\nVIP项目合作为高端用户提供专属服务，包括项目整体规划、全程深度指导、高质量保障和资源对接。特色是专属导师团队、深度定制方案、全程质量把控和资源优先对接，确保成果输出保障。"
    }
  ],
  "diyQA": [
    {
      "name": "基础版",
      "targetAudience": "科研入门者或首次投稿者",
      "customerPain": "不知道如何选题、如何开始科研写作、论文逻辑混乱",
      "serviceHighlight": "从选题到结构指导，涵盖基础科研思维建立 + 实用模板 + 精准反馈",
      "price": "¥99 起",
      "description": "5个问题",
      "serviceContent": "1. 问题快速响应\n2. 专人答疑服务\n3. 问题解决指导\n4. 后续跟进建议\n5. 邮件沟通支持",
      "serviceDetail": "## 服务概述\n\n基础版DIY答疑提供5个问题的快速响应服务，包括专人答疑、问题解决指导、后续跟进建议和邮件沟通支持。服务范围涵盖科研方法咨询、写作技巧指导和投稿流程解答。"
    },
    {
      "name": "高端答疑",
      "targetAudience": "正在系统进行科研项目/投稿者",
      "customerPain": "需要快速提升整体科研逻辑、规划思路、项目结构设计",
      "serviceHighlight": "10个问题+VIP专属答疑群，享受连续指导与长期支持",
      "price": "¥199 起",
      "description": "10个问题 + VIP服务群",
      "serviceContent": "1. 问题快速响应\n2. 专人答疑服务\n3. 问题解决指导\n4. 后续跟进建议\n5. 邮件沟通支持\n6. VIP专属答疑群\n7. 长期支持服务",
      "serviceDetail": "## 服务概述\n\n高端答疑提供10个问题的深度解答服务，包括12小时内响应、专人答疑、深度解答和VIP专属群支持。特色是快速响应、深度解答、专属群支持和长期服务，确保专业团队支持和全程保密。"
    }
  ],
  "diyDiagnosis": [
    {
      "name": "基础版",
      "targetAudience": "有科研基础，希望优化方向与结构的用户",
      "customerPain": "写了很多但总觉得不对、没有逻辑、效率低",
      "serviceHighlight": "由在读PhD（5篇以上SCI）提供30分钟深度辅导，定位问题核心",
      "price": "¥600 起",
      "description": "在读PhD（5篇以上SCI经验）30分钟",
      "serviceContent": "1. 深度辅导\n2. 问题核心定位\n3. 改进方案建议\n4. 结构优化指导\n5. 后续跟进支持",
      "serviceDetail": "## 服务概述\n\n基础版诊断由在读PhD提供30分钟深度辅导，包括论文分析、问题定位和改进建议。特色是专业诊断、深度分析和实用建议，确保专业团队支持和全程保密。"
    },
    {
      "name": "高级版",
      "targetAudience": "希望达到TOP期刊标准的研究者",
      "customerPain": "缺乏国际视野、学术表达和选题质量不足",
      "serviceHighlight": "由海外TOP高校PhD（10+SCI/顶会）提供结构化诊断与命中策略",
      "price": "¥1000 起",
      "description": "海内外TOP高校PhD（10篇+SCI或顶会）30分钟",
      "serviceContent": "1. 深度辅导\n2. 问题核心定位\n3. 改进方案建议\n4. 结构优化指导\n5. 后续跟进支持\n6. 国际视野指导\n7. 学术表达提升",
      "serviceDetail": "## 服务概述\n\n高级版诊断由海外TOP高校PhD提供30分钟结构化诊断，包括国际标准评估、创新性分析、学术价值评估和问题定位。特色是国际视野、专业诊断、深度分析和实用建议，确保专业团队支持和全程保密。"
    },
    {
      "name": "终极版",
      "targetAudience": "冲击权威期刊、高质量成果发表的用户",
      "customerPain": "不懂投稿规则、稿件被拒无从下手、缺乏编辑思维",
      "serviceHighlight": "由高校AP / SCI刊物编辑 / 审稿人提供高阶诊断，精准命中目标刊",
      "price": "¥2000 起",
      "description": "高校AP / 刊物编辑 / 审稿人 30分钟",
      "serviceContent": "1. 深度辅导\n2. 问题核心定位\n3. 改进方案建议\n4. 结构优化指导\n5. 后续跟进支持\n6. 国际视野指导\n7. 学术表达提升\n8. 编辑视角指导\n9. 投稿规则解读",
      "serviceDetail": "## 服务概述\n\n终极版诊断由高校AP/刊物编辑/审稿人提供30分钟高阶诊断，包括编辑视角评估、期刊标准分析、学术价值评估和问题定位。特色是编辑视角、专业诊断、深度分析、实用建议和期刊标准指导，确保专业团队支持和全程保密。"
    }
  ],
  "diagnosisServiceContent": [
    "帮助确定高命中率科研选题，提升研究价值",
    "梳理全文结构，优化段落逻辑和论证层级",
    "讲解投稿系统使用、Cover letter 撰写技巧",
    "针对目标期刊进行命中率评估与调整建议"
  ],
  "addOns": [
    {
      "name": "英文润色建议",
      "targetAudience": "非母语写作者或希望提高英文表达水平者",
      "customerPain": "语言不地道、表达不专业、影响审稿人观感",
      "serviceHighlight": "提供语法纠错+表达改进建议，适配学术英文风格",
      "price": "¥500",
      "serviceContent": "1. 语法纠错\n2. 表达改进建议\n3. 学术英文风格适配\n4. 专业术语优化\n5. 语言流畅度提升",
      "serviceDetail": "## 服务概述\n\n英文润色建议提供语法检查、表达评估、风格分析和改进建议。特色是专业润色、学术风格和表达优化，确保专业团队支持和全程保密。"
    },
    {
      "name": "图表美化建议",
      "targetAudience": "图表内容粗糙、结构混乱、表达不清晰者",
      "customerPain": "图表不专业、影响论文第一印象、易被拒稿",
      "serviceHighlight": "图示结构清晰化+美化建议，符合期刊审美与规范",
      "price": "¥300",
      "serviceContent": "1. 图表结构优化\n2. 视觉美化建议\n3. 期刊规范适配\n4. 信息表达清晰化\n5. 专业度提升",
      "serviceDetail": "## 服务概述\n\n图表美化建议提供图表结构评估、视觉分析和规范检查。特色是专业美化、规范适配和视觉优化，确保专业团队支持和全程保密。"
    },
    {
      "name": "审稿人推荐策略",
      "targetAudience": "希望提升命中率，精准推荐合适审稿人的用户",
      "customerPain": "不知道如何选审稿人、容易选错、投稿石沉大海",
      "serviceHighlight": "结合研究方向和目标期刊推荐合适审稿人群体",
      "price": "¥500",
      "serviceContent": "1. 审稿人筛选策略\n2. 研究方向匹配\n3. 期刊偏好分析\n4. 推荐名单制定\n5. 申请理由撰写",
      "serviceDetail": "## 服务概述\n\n审稿人推荐策略提供研究方向分析、期刊偏好分析和审稿人要求分析。特色是精准推荐、策略指导和专业分析，确保专业团队支持和全程保密。"
    },
    {
      "name": "催稿信撰写指导",
      "targetAudience": "投稿已久无反馈，想推动进度的投稿人",
      "customerPain": "不会写催稿信、语气难拿捏、怕被拒稿",
      "serviceHighlight": "提供高效催稿模板 + 外交性表达技巧，提升编辑回复率",
      "price": "¥200",
      "serviceContent": "1. 催稿信模板提供\n2. 外交性表达技巧\n3. 语气把控指导\n4. 编辑回复率提升\n5. 进度推动策略",
      "serviceDetail": "## 服务概述\n\n催稿信撰写指导提供投稿时间分析、期刊特点分析和催稿策略制定。特色是专业模板、表达技巧和策略指导，确保专业团队支持和全程保密。"
    },
    {
      "name": "查重优化建议",
      "targetAudience": "重复率过高、担心被判学术不端者",
      "customerPain": "担心抄袭检测、不会降重",
      "serviceHighlight": "针对检测结果提供可操作性重写建议，降低重复率",
      "price": "¥400",
      "serviceContent": "1. 查重结果分析\n2. 降重策略制定\n3. 可操作性重写建议\n4. 学术不端风险规避\n5. 重复率降低指导",
      "serviceDetail": "## 服务概述\n\n查重优化建议提供查重报告分析、问题定位和风险评估。特色是专业分析、策略指导和风险规避，确保专业团队支持和全程保密。"
    },
    {
      "name": "图表排版建议",
      "targetAudience": "希望图表符合特定期刊格式要求者",
      "customerPain": "图表混乱、格式不统一、被要求重排",
      "serviceHighlight": "为每张图表匹配标准格式，符合目标期刊规范",
      "price": "¥300",
      "serviceContent": "1. 图表格式标准化\n2. 期刊规范适配\n3. 格式统一整理\n4. 重排需求解决\n5. 专业度提升",
      "serviceDetail": "## 服务概述\n\n图表格式整理建议提供图表格式分析、规范分析和问题定位。特色是专业整理、规范适配和统一标准，确保专业团队支持和全程保密。"
    }
  ],
  "websiteInfo": {
    "name": "云起工作室",
    "slogan": "科研投稿咨询与指导服务",
    "introduction": "本平台聚焦科研投稿辅导与科研成长陪跑服务，覆盖自然科学、人文社科、医药学等多个学科。",
    "serviceScope": "我们提供高质量服务：选题指导、逻辑搭建、返修应对、投前把脉、母语润色、核心内容提炼、投稿流程陪跑等一站式解决方案。",
    "aboutUs": "云起工作室由海内外TOP高校PhD组成，与知名刊物编辑、985高校审稿人建立了广泛合作。致力于为科研投稿过程提供策略性支持与个性化辅导，已协助多名本硕博作者成功发表SCI、SSCI、核心期刊论文。",
    "servicePhilosophy": "我们重视合规、注重逻辑、善于规划，并持续拓展答疑服务、润色、科研诊断、文书定制、研究设计与留学就业辅导。",
    "contactInfo": {
      "wechat": {
        "account": "linker629",
        "qrcode": "images/wechat_qr.png"
      },
      "wechat_cooperation": {
        "account": "aifasci",
        "qrcode": "images/wechat_cooperation_qr.png"
      },
      "email": {
        "address": "scientific_paper@gmail.com",
        "workingHours": "周一至周五 9:00-18:00",
        "responseTime": "24小时内",
        "urgentConsultation": "如需紧急咨询，请添加微信"
      },
      "consultationGroup": {
        "qrcode": "images/group_qr.png"
      }
    },
    "copyrightInfo": {
      "year": "2025",
      "name": "云起工作室",
      "description": "版权所有"
    }
  }
}